setup.py
datastore/__init__.py
datastore.objects.egg-info/PKG-INFO
datastore.objects.egg-info/SOURCES.txt
datastore.objects.egg-info/dependency_links.txt
datastore.objects.egg-info/namespace_packages.txt
datastore.objects.egg-info/requires.txt
datastore.objects.egg-info/top_level.txt
datastore/core/__init__.py
datastore/core/basic.py
datastore/core/key.py
datastore/core/query.py
datastore/core/serialize.py
datastore/core/test/__init__.py
datastore/core/test/test_basic.py
datastore/core/test/test_key.py
datastore/core/test/test_query.py
datastore/core/test/test_serialize.py
datastore/core/util/__init__.py
datastore/core/util/fasthash.py
datastore/objects/__init__.py
datastore/objects/attribute.py
datastore/objects/attribute_metaclass.py
datastore/objects/collection.py
datastore/objects/collection_manager.py
datastore/objects/manager.py
datastore/objects/model.py
datastore/objects/object_datastore.py
datastore/objects/util.py
datastore/objects/test/__init__.py
datastore/objects/test/test_objects.py
datastore/objects/test/test_objects_attribute.py
datastore/objects/test/test_objects_attribute_metaclass.py
datastore/objects/test/test_objects_collection.py
datastore/objects/test/test_objects_collection_manager.py
datastore/objects/test/test_objects_manager.py
datastore/objects/test/test_objects_model.py
datastore/objects/test/test_objects_object_datastore.py
datastore/objects/test/test_objects_util.py