Metadata-Version: 1.0
Name: datastore.objects
Version: 0.2.3
Summary: object mapper for datastore
Home-page: http://github.com/datastore/datastore.objects
Author: Juan Batiz-Benet
Author-email: juan@benet.ai
License: MIT License
Keywords: datastore,object mapper,ORM,serializing
Platform: UNKNOWN
Classifier: Topic :: Database
